README.md
setup.cfg
setup.py
examples/__init__.py
examples/cv/__init__.py
examples/cv/table_ex1/__init__.py
examples/cv/table_ex1/read_picture.py
examples/cv/table_ex1/table_detection.py
examples/cv/table_ex2/__init__.py
examples/cv/table_ex2/extract_docx_table.py
examples/cv/table_ex2/extract_pdf_table.py
examples/cv/table_ex2/out/__init__.py
examples/cv/table_ex2/test/__init__.py
examples/cv/utils/2.3.make_main_txt.py
examples/cv/utils/2.coco2voc.py
examples/cv/utils/__init__.py
examples/cv/utils/table-cell-to-coco.py
examples/opspipe/TOTP.py
examples/opspipe/__init__.py
examples/opspipe/DevOps/__init__.py
examples/opspipe/DevOps/deploy/TestDockerClient.py
examples/opspipe/DevOps/deploy/TestGitClient.py
examples/opspipe/DevOps/deploy/__init__.py
examples/opspipe/app/__init__.py
examples/opspipe/app/runserver.py
examples/opspipe/app/test_BackgroundTasks.py
examples/opspipe/app/test_upload.py
examples/opspipe/app/code/__init__.py
examples/opspipe/app/code/logging/__init__.py
examples/opspipe/app/code/logging/test.py
examples/opspipe/app/model/__init__.py
examples/opspipe/app/model/runserver.py
examples/opspipe/reg/__init__.py
examples/opspipe/reg/test_base.py
examples/opspipe/reg/test_common.py
examples/opspipe/reg/test_scanner.py
examples/opspipe/reg/test_spliter.py
examples/opspipe/test/__init__.py
examples/opspipe/test/construction_enterprise_qualification_certificate.py
examples/opspipe/test/runserver.py
opspipe/__init__.py
opspipe.egg-info/PKG-INFO
opspipe.egg-info/SOURCES.txt
opspipe.egg-info/dependency_links.txt
opspipe.egg-info/requires.txt
opspipe.egg-info/top_level.txt
opspipe/app/__init__.py
opspipe/app/main.py
opspipe/app/core/__init__.py
opspipe/app/core/aip/__init__.py
opspipe/app/core/events/__init__.py
opspipe/app/core/events/events.py
opspipe/app/core/logging/__init__.py
opspipe/app/core/logging/logging.py
opspipe/app/core/middleware/__init__.py
opspipe/app/core/middleware/middleware.py
opspipe/app/core/openapi/__init__.py
opspipe/app/core/openapi/converter.py
opspipe/app/core/redis/__init__.py
opspipe/app/core/redis/redis.py
opspipe/app/core/response/BaseResponse.py
