Metadata-Version: 2.1
Name: opspipe
Version: 0.0.24
Summary: This is the ml pipeline
Home-page: https://gitee.com/zhys513/opspipe
Author: zhys513
Author-email: 254851907@qq.com
License: UNKNOWN
Platform: UNKNOWN
Requires-Python: >=3.6
